flowjax_py39/__init__.py
flowjax_py39/bijections/__init__.py
flowjax_py39/bijections/affine.py
flowjax_py39/bijections/bijection.py
flowjax_py39/bijections/block_autoregressive_network.py
flowjax_py39/bijections/chain.py
flowjax_py39/bijections/concatenate.py
flowjax_py39/bijections/coupling.py
flowjax_py39/bijections/exp.py
flowjax_py39/bijections/jax_transforms.py
flowjax_py39/bijections/masked_autoregressive.py
flowjax_py39/bijections/orthogonal.py
flowjax_py39/bijections/planar.py
flowjax_py39/bijections/power.py
flowjax_py39/bijections/rational_quadratic_spline.py
flowjax_py39/bijections/sigmoid.py
flowjax_py39/bijections/softplus.py
flowjax_py39/bijections/tanh.py
flowjax_py39/bijections/utils.py
flowjax_py39/distributions.py
flowjax_py39/experimental/__init__.py
flowjax_py39/experimental/numpyro.py
flowjax_py39/flows.py
flowjax_py39/masks.py
flowjax_py39/py.typed
flowjax_py39/root_finding.py
flowjax_py39/tasks.py
flowjax_py39/train/__init__.py
flowjax_py39/train/loops.py
flowjax_py39/train/losses.py
flowjax_py39/train/train_utils.py
flowjax_py39/utils.py
flowjax_py39-17.1.2.1.dist-info/WHEEL
flowjax_py39-17.1.2.1.dist-info/METADATA
flowjax_py39-17.1.2.1.dist-info/RECORD
