Metadata-Version: 2.3
Name: flowjax-py39
Version: 17.1.2.1
Summary: Easy to use distributions, bijections and normalizing flows in JAX, forked for Python 3.9 compatability
Keywords: jax,neural-networks,equinox
Author: Joshua Chen
Author-email: Joshua Chen <joshuawchen@icloud.com>
License: The MIT License (MIT)
Requires-Dist: jax>=0.4.16
Requires-Dist: equinox<=0.11.10
Requires-Dist: jaxtyping
Requires-Dist: paramax-py39>=0.0.3.1
Requires-Dist: tqdm
Requires-Dist: optax
Requires-Dist: pytest ; extra == 'dev'
Requires-Dist: beartype ; extra == 'dev'
Requires-Dist: ruff ; extra == 'dev'
Requires-Dist: sphinx<8.2 ; extra == 'dev'
Requires-Dist: sphinx-book-theme ; extra == 'dev'
Requires-Dist: sphinx-copybutton ; extra == 'dev'
Requires-Dist: sphinx-autodoc-typehints ; extra == 'dev'
Requires-Dist: nbsphinx ; extra == 'dev'
Requires-Dist: ipython ; extra == 'dev'
Requires-Dist: numpyro ; extra == 'dev'
Requires-Python: >=3.9
Project-URL: documentation, https://danielward27.github.io/flowjax/index.html
Project-URL: repository, https://github.com/joshuawchen/flowjax_py39
Provides-Extra: dev
